Workbook
Name Electrolux: MasterData!$K$2
Name Hatco: MasterData!$L$2:$L$6582
Name Morello_Forni: MasterData!$M$2
Name Robot_Coupe: MasterData!$N$2:$N$6
Name Santos: MasterData!$O$2:$O$4453
Name Sirman: MasterData!$P$2:$P$6
Name T_S: MasterData!$Q$2:$Q$5

Sheet MasterData
A1: Brand | B1: ModelNo | C1: Description | D1: HSN | E1: UOM | F1: Rate | G1: GSTRate
A2: Electrolux | B2: 9PDD229798 | C2: SKYLINE PREMIUMS OVEN 20 GN 2/1 - ELECTRIC - BOILER AISI 316L - 3-GLASS | D2: 84198190 | E2: PCS | F2: 2450000 | G2: 18 | J2: Electrolux | K2: 9PDD229798 | L2: 01.05.003.00 | M2: MF.02.007 | N2: 303051 | O2: 00001B | P2: LF1532000I | Q2: EX-1DP00-H
A3: Hatco | B3: 01.05.003.00 | C3: PMG-60 SS TANK ASSY | E3: PCS | F3: 62989.41 | G3: 18 | J3: Hatco | L3: 01.05.005.00 | N3: 49521 | O3: 00002N | P3: LF1532060I2 | Q3: EX-1DP12-H
A4: Hatco | B4: 01.05.005.00 | C4: PMG-100,200 SS TANK ASSY | E4: PCS | F4: 59101.812 | G4: 18 | J4: Morello Forni | L4: 01.05.005.OS | N4: 500289S | O4: 00063R | P4: LF1532080I2 | Q4: EX-6WP00-H
A5: Hatco | B5: 01.05.005.OS | C5: PMG-100,200 SS TANK ASSY,OS | E5: PCS | F5: 62989.41 | G5: 18 | J5: Robot Coupe | L5: 02.01.007.00 | N5: 600018S | O5: 01100N | P5: MF2215PS | Q5: EX-6WP12-H
A6: Hatco | B6: 02.01.007.00 | C6: REL,OPEN,240AC,SPDT,30RES | E6: PCS | F6: 5744.112 | G6: 18 | J6: Santos | L6: 02.01.008.00 | N6: 89136 | O6: 01102N | P6: MF2220
A7: Hatco | B7: 02.01.008.00 | C7: REL,OPEN,208/240AC,DPST,30RES | E7: PCS | F7: 5091.372 | G7: 18 | J7: Sirman | L7: 02.01.010.00 | O7: 01103BAR
A8: Hatco | B8: 02.01.010.00 | C8: REL,OPEN,120AC,2PST,30RES | E8: PCS | F8: 5091.372 | G8: 18 | J8: T&S | L8: 02.01.015.00 | O8: 01105N
A9: Hatco | B9: 02.01.015.00 | C9: CON,STD,110/120AC,3P,50RES | E9: PCS | F9: 6919.044 | G9: 18 | L9: 02.01.016.00 | O9: 01200B
A10: Hatco | B10: 02.01.016.00 | C10: CON,STD,208/240AC,3P,50RES | E10: PCS | F10: 6919.044 | G10: 18 | L10: 02.01.017.00 | O10: 01200P
A11: Hatco | B11: 02.01.017.00 | C11: CON,STD,110/120AC,4P,50RES | E11: PCS | F11: 6919.044 | G11: 18 | L11: 02.01.018.00 | O11: 01200PV
A12: Hatco | B12: 02.01.018.00 | C12: CON,STD,208/240AC,4P,50RES | E12: PCS | F12: 7506.51 | G12: 18 | L12: 02.01.028.00 | O12: 01201PV
A13: Hatco | B13: 02.01.028.00 | C13: REL,CUBE,120AC,SPDTLATC,10RES | E13: PCS | F13: 6396.852 | G13: 18 | L13: 02.01.031.00 | O13: 01214N
A14: Hatco | B14: 02.01.031.00 | C14: REL,CUBE,120AC,3PDT,10RES | E14: PCS | F14: 6592.674 | G14: 18 | L14: 02.01.040.00 | O14: 01214PV
A15: Hatco | B15: 02.01.040.00 | C15: CON,STD,110/120AC,2P,50RES | E15: PCS | F15: 5939.934 | G15: 18 | L15: 02.01.043.00 | O15: 01223P
A16: Hatco | B16: 02.01.043.00 | C16: REL,CUBE,240AC,SPDTPLATC,10RES | E16: PCS | F16: 10770.21 | G16: 18 | L16: 02.01.049.00 | O16: 01225B
A17: Hatco | B17: 02.01.049.00 | C17: T-STAT CONT SS 24VDC OUT FAR | E17: PCS | F17: 18276.72 | G17: 18 | L17: 02.01.056.00 | O17: 01225P
A18: Hatco | B18: 02.01.056.00 | C18: T-STAT PROBE 3-CON 36" FAR | E18: PCS | F18: 2937.33 | G18: 18 | L18: 02.01.057.00 | O18: 01225PV
A19: Hatco | B19: 02.01.057.00 | C19: T-STAT PROBE 3-CON 48" FAR | E19: PCS | F19: 3785.892 | G19: 18 | L19: 02.01.061.00 | O19: 01235B
A20: Hatco | B20: 02.01.061.00 | C20: REL,MICRO,24DC,SPDT,10RES | E20: PCS | F20: 2937.33 | G20: 18 | L20: 02.01.073.00 | O20: 01239B
... A3145: Hatco | B3145: 05.03.022.00 | C3145: CHAIN S.S. TQ-300 CONVEYOR | E3145: PCS | F3145: 6984.318 | G3145: 18 | L3145: 05.03.035.00 | O3145: 55840BM
A3146: Hatco | B3146: 05.03.035.00 | C3146: WIRE BELT,10x.5x72 LINKS | D3146: 73141490 | E3146: PCS | F3146: 8485.62 | G3146: 18 | L3146: 05.03.036.00 | O3146: 55840N
A3147: Hatco | B3147: 05.03.036.00 | C3147: WIRE BELT,10x.5x51 LINKS | E3147: PCS | F3147: 7245.414 | G3147: 18 | L3147: 05.03.037.00 | O3147: 55841
A3148: Hatco | B3148: 05.03.037.00 | C3148: CHAIN 30 PITCH W/LINK | E3148: PCS | F3148: 522.192 | G3148: 18 | L3148: 05.03.038.00 | O3148: 55841A
A3149: Hatco | B3149: 05.03.038.00 | C3149: CHAIN 35 PITCH | E3149: PCS | F3149: 587.466 | G3149: 18 | L3149: 05.03.039.00 | O3149: 55841C
A3150: Hatco | B3150: 05.03.039.00 | C3150: CABLE PULLBOX PLUS 5LB | E3150: PCS | F3150: 3981.714 | G3150: 18 | L3150: 05.03.046.00 | O3150: 55843
A3151: Hatco | B3151: 05.03.046.00 | C3151: WIRE BELT,14x.5x72 LINKS | E3151: PCS | F3151: 17101.788 | G3151: 18 | L3151: 05.03.049.00 | O3151: 55845
A3152: Hatco | B3152: 05.03.049.00 | C3152: CHAIN,ROLLER,1/4P X 1/8W 14"L | E3152: PCS | F3152: 326.37 | G3152: 18 | L3152: 05.03.053.00 | O3152: 55847
A3153: Hatco | B3153: 05.03.053.00 | C3153: CHAIN,14 GA,6.5",SINGLE,STEEL | E3153: PCS | F3153: 195.822 | G3153: 18 | L3153: 05.03.054.00 | O3153: 55849
A3154: Hatco | B3154: 05.03.054.00 | C3154: S-HOOK,CLOSED,.121 X 1,STEEL | E3154: PCS | F3154: 130.548 | G3154: 18 | L3154: 05.03.055.01 | O3154: 55849BM
A3155: Hatco | B3155: 05.03.055.01 | C3155: MECHANICAL REEL,BASE MT,0.5LB | E3155: PCS | F3155: 12597.882 | G3155: 18 | L3155: 05.03.055.02 | O3155: 55851
A3156: Hatco | B3156: 05.03.055.02 | C3156: MECHANICAL REEL,BASE MT,1.0LB | E3156: PCS | F3156: 12597.882 | G3156: 18 | L3156: 05.03.056.00 | O3156: 55852
A3157: Hatco | B3157: 05.03.056.00 | C3157: CHAIN,ROLL,1/4P X 1/8W 14.5"L | E3157: PCS | F3157: 1892.946 | G3157: 18 | L3157: 05.03.057.00 | O3157: 55854
A3158: Hatco | B3158: 05.03.057.00 | C3158: WIRE BELT,6.875x.5x51 LINKS | E3158: PCS | F3158: 7832.88 | G3158: 18 | L3158: 05.03.062.00 | O3158: 55855
... A4453: Hatco | B4453: R00.02.0225.00 | C4453: KIT,LAMP ASSY INVZBL Z13 | E4453: PCS | F4453: 7114.866 | G4453: 18 | L4453: R00.02.0226.00 | O4453: TABLE
A4454: Hatco | B4454: R00.02.0226.00 | C4454: KIT,RHW-B HARNESS ASSEMBLY | E4454: PCS | F4454: 2349.864 | G4454: 18 | L4454: R00.02.0227.00
A4455: Hatco | B4455: R00.02.0227.00 | C4455: KIT,DIN TBLOCK ASSY MINNOW | E4455: PCS | F4455: 5744.112 | G4455: 18 | L4455: R00.02.0228.00
A4456: Hatco | B4456: R00.02.0228.00 | C4456: ELEC CONT,IMP RETROFIT 3 ELEMT | E4456: PCS | F4456: 28524.738 | G4456: 18 | L4456: R00.02.0229.00
A4457: Hatco | B4457: R00.02.0229.00 | C4457: ELEC CONT,IMP RETROFIT 6 ELEMT | E4457: PCS | F4457: 38576.934 | G4457: 18 | L4457: R00.02.0230.00
A4458: Hatco | B4458: R00.02.0230.00 | C4458: ELEC CONT,IMP RETROFIT 9 ELEMT | E4458: PCS | F4458: 42297.552 | G4458: 18 | L4458: R00.02.0231.00
A4459: Hatco | B4459: R00.02.0231.00 | C4459: KIT,CONTROL BOX ASSY,IRNG-PB2 | E4459: PCS | F4459: 46866.732 | G4459: 18 | L4459: R00.02.0232.00
A4460: Hatco | B4460: R00.02.0232.00 | C4460: KIT,CONTROL BOX ASSY CWBR 120V | E4460: PCS | F4460: 28394.19 | G4460: 18 | L4460: R00.02.0233.00
A4461: Hatco | B4461: R00.02.0233.00 | C4461: KIT,HBGBHC-2418 W/TRIM | E4461: PCS | F4461: 38707.482 | G4461: 18 | L4461: R00.02.0234.00
A4462: Hatco | B4462: R00.02.0234.00 | C4462: KIT,HBGBHC-2418 W/O TRIM | E4462: PCS | F4462: 32375.904 | G4462: 18 | L4462: R00.02.0238.00
A4463: Hatco | B4463: R00.02.0238.00 | C4463: KIT,HBGBHC-3618 W/O TRIM | E4463: PCS | F4463: 39621.318 | G4463: 18 | L4463: R00.02.0239.00
A4464: Hatco | B4464: R00.02.0239.00 | C4464: KIT,HBGBHC-4818 W/TRIM | E4464: PCS | F4464: 55613.448 | G4464: 18 | L4464: R00.02.0245.00
A4465: Hatco | B4465: R00.02.0245.00 | C4465: CNTRL BOX,SMALL FLUSH,TSTAT | E4465: PCS | F4465: 29046.93 | G4465: 18 | L4465: R00.02.0246.00
... A6582: Hatco | B6582: X07.03.566.00 | C6582: SERVICE,OVERLAY,FMSS-7 | E6582: PCS | F6582: 261.096 | G6582: 18 | L6582: X07.03.939.00
A6583: Hatco | B6583: X07.03.939.00 | C6583: PANEL DECAL,QTS-1 | E6583: PCS | F6583: 4830.276 | G6583: 18
A6584: Morello Forni | B6584: MF.02.007 | C6584: Triple electrode dome | E6584: PCS | F6584: 27596 | G6584: 18
A6585: Robot Coupe | B6585: 303051 | C6585: MOTOR R5A+/R6A 400 V | E6585: PCS | F6585: 129295 | G6585: 18
A6586: Robot Coupe | B6586: 49521 | C6586: MOTOR ASSEMBLY 4/8 POLES H105 400/50/3 | E6586: PCS | F6586: 129295 | G6586: 18
A6587: Robot Coupe | B6587: 500289S | C6587: MOTOR STARTING RELAY MTRPH 46-39 | D6587: 85364900 | E6587: PCS | F6587: 1944 | G6587: 18
A6588: Robot Coupe | B6588: 600018S | C6588: CAPACITOR 60ΜF 250V | D6588: 85322990 | E6588: PCS | F6588: 1856 | G6588: 18
A6589: Robot Coupe | B6589: 89136 | C6589: POWER CORD MP/CMP EUR | D6589: 84389090 | E6589: PCS | F6589: 2768 | G6589: 18
A6590: Santos | B6590: 00001B | C6590: SET OF 2 SANTOS GRINDING DISCS HIGH OUTPUT | E6590: PCS | F6590: 5228.3 | G6590: 18
A6591: Santos | B6591: 00002N | C6591: SET OF 2 SPICES GRINDING DISCS (PEPPER) | E6591: PCS | F6591: 5387.8 | G6591: 18
A6592: Santos | B6592: 00063R | C6592: SET OF 2 SANTOS GRINDING DISCS DIAM 120 mm Resharpened | E6592: PCS | F6592: 28818.9 | G6592: 18
A6593: Santos | B6593: 01100N | C6593: COMPLETE BLACK HOPPER WITH OBTURATOR pour 01BAR | E6593: PCS | F6593: 4722.3 | G6593: 18
A6594: Santos | B6594: 01102N | C6594: BLACK HOPPER | E6594: PCS | F6594: 2092.2 | G6594: 18
A6595: Santos | B6595: 01103BAR | C6595: OBTURATOR with drilled hole for 01BAR | E6595: PCS | F6595: 1487.2 | G6595: 18
A6596: Santos | B6596: 01105N | C6596: SCREW CX 4 X 70 Zn | E6596: PCS | F6596: 201.3 | G6596: 18
A6597: Santos | B6597: 01200B | C6597: COMPLETE GRIND HOUSING 60Hz | E6597: PCS | F6597: 55376.2 | G6597: 18
A6598: Santos | B6598: 01200P | C6598: COMPLETE GRIND HOUSING (PEPPER - SPICES) | E6598: PCS | F6598: 52649.3 | G6598: 18
A6599: Santos | B6599: 01200PV | C6599: COMPLETE GRIND HOUSING (POPPY) | E6599: PCS | F6599: 58105.3 | G6599: 18
A6600: Santos | B6600: 01201PV | C6600: GRIND HOUSING WITH ADJUSTING BUTTON Special Poppy (01PV) | E6600: PCS | F6600: 25168 | G6600: 18
A6601: Santos | B6601: 01214N | C6601: BLACK GRIND HOUSING | E6601: PCS | F6601: 14781.8 | G6601: 18
... A9166: Santos | B9166: 50151 | C9166: TOP COVER | E9166: PCS | F9166: 7496.5 | G9166: 18
A9167: Santos | B9167: 50200 | C9167: COMPLETE BASKET ASSEMBLY | D9167: 84389090 | E9167: PCS | F9167: 22606.1 | G9167: 18
A9168: Santos | B9168: 50200B | C9168: COMPLET BASKETSPECIAL, HOLES 0,8 | E9168: PCS | F9168: 22606.1 | G9168: 18
A9169: Santos | B9169: 50200C | C9169: AUTOCLEAN COMPLETE BASKET ASSEMBLY | E9169: PCS | F9169: 30934.2 | G9169: 18
A9170: Santos | B9170: 50201 | C9170: CAP NUT H M 8 S.STEEL | E9170: PCS | F9170: 308 | G9170: 18
A9171: Santos | B9171: 50202 | C9171: WASHER 8X130 | E9171: PCS | F9171: 92.4 | G9171: 18
A9172: Santos | B9172: 50203 | C9172: FRUIT CENTER KNIFE SCREW | E9172: PCS | F9172: 1640.1 | G9172: 18
A9173: Santos | B9173: 50210 | C9173: GRATING DISC (BLADE) | E9173: PCS | F9173: 1901.9 | G9173: 18
A9174: Santos | B9174: 50220 | C9174: BASKET | E9174: PCS | F9174: 14696 | G9174: 18
A9175: Santos | B9175: 50220B | C9175: BASKET, SPECIAL, HOLES 0.8 | E9175: PCS | F9175: 14696 | G9175: 18
A9176: Santos | B9176: 50220C | C9176: AUTOCLEAN BASKET | E9176: PCS | F9176: 28889.3 | G9176: 18
A9177: Santos | B9177: 50230 | C9177: BASKET BASE | E9177: PCS | F9177: 4206.4 | G9177: 18
A9178: Santos | B9178: 50250 | C9178: GRATING DISC + SCREWS REPLACEMENT SET | E9178: PCS | F9178: 5197.5 | G9178: 18
A9179: Santos | B9179: 50300 | C9179: BOWL | E9179: PCS | F9179: 13756.6 | G9179: 18
... A10609: Santos | B10609: 68110 | C10609: PATISSERIE PACK FOR JUICE EXTRACTOR 68 | E10609: PCS | F10609: 62664.8 | G10609: 18
A10610: Santos | B10610: 68200 | C10610: COMPLETE BASKET STANDARD WITH BLADE | D10610: 84389090 | E10610: PCS | F10610: 36883 | G10610: 18
A10611: Santos | B10611: 68200B | C10611: COMPLETE BASKET-HOLES 0,8MM - WITH BLADE | E10611: PCS | F10611: 36883 | G10611: 18
A10612: Santos | B10612: 68200C | C10612: COMPLETE AUTOCLEAN BASKET WITH BLADE | E10612: PCS | F10612: 44387.2 | G10612: 18
A10613: Santos | B10613: 68200S | C10613: COMPLETE BASKET STANDARD WITH SHARP BLADE | E10613: PCS | F10613: 36608 | G10613: 18
A10614: Santos | B10614: 68202 | C10614: BLADE (DISC) ONLY 68 | E10614: PCS | F10614: 6063.2 | G10614: 18
A10615: Santos | B10615: 68202S | C10615: SHARP BLADE (DISC) ONLY 68 | E10615: PCS | F10615: 5376.8 | G10615: 18
A10616: Santos | B10616: 68205 | C10616: SCREW F90 M5x12 S.STEEL | E10616: PCS | F10616: 140.8 | G10616: 18
A10617: Santos | B10617: 68206 | C10617: WASHER GROWER W5 | E10617: PCS | F10617: 58.3 | G10617: 18
A10618: Santos | B10618: 68207 | C10618: CAP NUT H M 5 | E10618: PCS | F10618: 161.7 | G10618: 18
A10619: Santos | B10619: 68210 | C10619: BASKET (STRAINER) ONLY STANDARD | E10619: PCS | F10619: 30826.4 | G10619: 18
A10620: Santos | B10620: 68210B | C10620: BASKET (STRAINER) ONLY DIAM 0.8 MM | E10620: PCS | F10620: 30773.6 | G10620: 18
A10621: Santos | B10621: 68210C | C10621: BASKET (STRAINER) ONLY AUTOCLEAN | E10621: PCS | F10621: 33404.8 | G10621: 18
A10622: Santos | B10622: 68213 | C10622: BASKET BASE SEAL | E10622: PCS | F10622: 247.5 | G10622: 18
... A11044: Sirman | B11044: LF1532080I2 | C11044: S/S PLATE MM 8 FOR TC 22 _ 2C | E11044: PCS | F11044: 0 | G11044: 18
A11045: Sirman | B11045: MF2215PS | C11045: WORM+WORM-PIN CAST-IRON TC 22 E | D11045: 84389090 | E11045: PCS | F11045: 13651 | G11045: 18
A11046: Sirman | B11046: MF2220 | C11046: ALUMINUM WHEEL TC/TCG22E | E11046: PCS | F11046: 0 | G11046: 18
A11047: T&S | B11047: EX-1DP00-H | C11047: Pre-Rinse Unit | D11047: 848180 | E11047: PCS | F11047: 16100 | G11047: 18
A11048: T&S | B11048: EX-1DP12-H | C11048: Pre-Rinse Unit | D11048: 848180 | E11048: PCS | F11048: 20700 | G11048: 18
...

Sheet Quotation
A1: QUOTATION
A3: Sl. No. | B3: Brand | C3: Model No/Part Code | D3: Description | E3: HSN Code | F3: UOM | G3: QTY | H3: Unit Rate (₹) | I3: Taxable Value (₹) | J3: GST Rate (%) | K3: GST Value (₹) | L3: Total Value (₹)
A4: =IF(C4<>"", ROW()-3, "") | D4: =IFERROR(VLOOKUP(C4, MasterData!B:G, 2, FALSE), "") | E4: =IFERROR(VLOOKUP(C4, MasterData!B:G, 3, FALSE), "") | F4: =IFERROR(VLOOKUP(C4, MasterData!B:G, 4, FALSE), "") | H4: =IFERROR(VLOOKUP(C4, MasterData!B:G, 5, FALSE), "") | I4: =IF(AND(G4<>"", H4<>""), G4*H4, "") | J4: =IFERROR(VLOOKUP(C4, MasterData!B:G, 6, FALSE), 18) | K4: =IF(I4<>"", I4*J4/100, "") | L4: =IF(I4<>"", I4+K4, "")
A5: =IF(C5<>"", ROW()-3, "") | D5: =IFERROR(VLOOKUP(C5, MasterData!B:G, 2, FALSE), "") | E5: =IFERROR(VLOOKUP(C5, MasterData!B:G, 3, FALSE), "") | F5: =IFERROR(VLOOKUP(C5, MasterData!B:G, 4, FALSE), "") | H5: =IFERROR(VLOOKUP(C5, MasterData!B:G, 5, FALSE), "") | I5: =IF(AND(G5<>"", H5<>""), G5*H5, "") | J5: =IFERROR(VLOOKUP(C5, MasterData!B:G, 6, FALSE), 18) | K5: =IF(I5<>"", I5*J5/100, "") | L5: =IF(I5<>"", I5+K5, "")
A6: =IF(C6<>"", ROW()-3, "") | D6: =IFERROR(VLOOKUP(C6, MasterData!B:G, 2, FALSE), "") | E6: =IFERROR(VLOOKUP(C6, MasterData!B:G, 3, FALSE), "") | F6: =IFERROR(VLOOKUP(C6, MasterData!B:G, 4, FALSE), "") | H6: =IFERROR(VLOOKUP(C6, MasterData!B:G, 5, FALSE), "") | I6: =IF(AND(G6<>"", H6<>""), G6*H6, "") | J6: =IFERROR(VLOOKUP(C6, MasterData!B:G, 6, FALSE), 18) | K6: =IF(I6<>"", I6*J6/100, "") | L6: =IF(I6<>"", I6+K6, "")
A7: =IF(C7<>"", ROW()-3, "") | D7: =IFERROR(VLOOKUP(C7, MasterData!B:G, 2, FALSE), "") | E7: =IFERROR(VLOOKUP(C7, MasterData!B:G, 3, FALSE), "") | F7: =IFERROR(VLOOKUP(C7, MasterData!B:G, 4, FALSE), "") | H7: =IFERROR(VLOOKUP(C7, MasterData!B:G, 5, FALSE), "") | I7: =IF(AND(G7<>"", H7<>""), G7*H7, "") | J7: =IFERROR(VLOOKUP(C7, MasterData!B:G, 6, FALSE), 18) | K7: =IF(I7<>"", I7*J7/100, "") | L7: =IF(I7<>"", I7+K7, "")
A8: =IF(C8<>"", ROW()-3, "") | D8: =IFERROR(VLOOKUP(C8, MasterData!B:G, 2, FALSE), "") | E8: =IFERROR(VLOOKUP(C8, MasterData!B:G, 3, FALSE), "") | F8: =IFERROR(VLOOKUP(C8, MasterData!B:G, 4, FALSE), "") | H8: =IFERROR(VLOOKUP(C8, MasterData!B:G, 5, FALSE), "") | I8: =IF(AND(G8<>"", H8<>""), G8*H8, "") | J8: =IFERROR(VLOOKUP(C8, MasterData!B:G, 6, FALSE), 18) | K8: =IF(I8<>"", I8*J8/100, "") | L8: =IF(I8<>"", I8+K8, "")
A9: =IF(C9<>"", ROW()-3, "") | D9: =IFERROR(VLOOKUP(C9, MasterData!B:G, 2, FALSE), "") | E9: =IFERROR(VLOOKUP(C9, MasterData!B:G, 3, FALSE), "") | F9: =IFERROR(VLOOKUP(C9, MasterData!B:G, 4, FALSE), "") | H9: =IFERROR(VLOOKUP(C9, MasterData!B:G, 5, FALSE), "") | I9: =IF(AND(G9<>"", H9<>""), G9*H9, "") | J9: =IFERROR(VLOOKUP(C9, MasterData!B:G, 6, FALSE), 18) | K9: =IF(I9<>"", I9*J9/100, "") | L9: =IF(I9<>"", I9+K9, "")
A10: =IF(C10<>"", ROW()-3, "") | D10: =IFERROR(VLOOKUP(C10, MasterData!B:G, 2, FALSE), "") | E10: =IFERROR(VLOOKUP(C10, MasterData!B:G, 3, FALSE), "") | F10: =IFERROR(VLOOKUP(C10, MasterData!B:G, 4, FALSE), "") | H10: =IFERROR(VLOOKUP(C10, MasterData!B:G, 5, FALSE), "") | I10: =IF(AND(G10<>"", H10<>""), G10*H10, "") | J10: =IFERROR(VLOOKUP(C10, MasterData!B:G, 6, FALSE), 18) | K10: =IF(I10<>"", I10*J10/100, "") | L10: =IF(I10<>"", I10+K10, "")
A11: =IF(C11<>"", ROW()-3, "") | D11: =IFERROR(VLOOKUP(C11, MasterData!B:G, 2, FALSE), "") | E11: =IFERROR(VLOOKUP(C11, MasterData!B:G, 3, FALSE), "") | F11: =IFERROR(VLOOKUP(C11, MasterData!B:G, 4, FALSE), "") | H11: =IFERROR(VLOOKUP(C11, MasterData!B:G, 5, FALSE), "") | I11: =IF(AND(G11<>"", H11<>""), G11*H11, "") | J11: =IFERROR(VLOOKUP(C11, MasterData!B:G, 6, FALSE), 18) | K11: =IF(I11<>"", I11*J11/100, "") | L11: =IF(I11<>"", I11+K11, "")
A12: =IF(C12<>"", ROW()-3, "") | D12: =IFERROR(VLOOKUP(C12, MasterData!B:G, 2, FALSE), "") | E12: =IFERROR(VLOOKUP(C12, MasterData!B:G, 3, FALSE), "") | F12: =IFERROR(VLOOKUP(C12, MasterData!B:G, 4, FALSE), "") | H12: =IFERROR(VLOOKUP(C12, MasterData!B:G, 5, FALSE), "") | I12: =IF(AND(G12<>"", H12<>""), G12*H12, "") | J12: =IFERROR(VLOOKUP(C12, MasterData!B:G, 6, FALSE), 18) | K12: =IF(I12<>"", I12*J12/100, "") | L12: =IF(I12<>"", I12+K12, "")
A13: =IF(C13<>"", ROW()-3, "") | D13: =IFERROR(VLOOKUP(C13, MasterData!B:G, 2, FALSE), "") | E13: =IFERROR(VLOOKUP(C13, MasterData!B:G, 3, FALSE), "") | F13: =IFERROR(VLOOKUP(C13, MasterData!B:G, 4, FALSE), "") | H13: =IFERROR(VLOOKUP(C13, MasterData!B:G, 5, FALSE), "") | I13: =IF(AND(G13<>"", H13<>""), G13*H13, "") | J13: =IFERROR(VLOOKUP(C13, MasterData!B:G, 6, FALSE), 18) | K13: =IF(I13<>"", I13*J13/100, "") | L13: =IF(I13<>"", I13+K13, "")
A14: =IF(C14<>"", ROW()-3, "") | D14: =IFERROR(VLOOKUP(C14, MasterData!B:G, 2, FALSE), "") | E14: =IFERROR(VLOOKUP(C14, MasterData!B:G, 3, FALSE), "") | F14: =IFERROR(VLOOKUP(C14, MasterData!B:G, 4, FALSE), "") | H14: =IFERROR(VLOOKUP(C14, MasterData!B:G, 5, FALSE), "") | I14: =IF(AND(G14<>"", H14<>""), G14*H14, "") | J14: =IFERROR(VLOOKUP(C14, MasterData!B:G, 6, FALSE), 18) | K14: =IF(I14<>"", I14*J14/100, "") | L14: =IF(I14<>"", I14+K14, "")
A15: =IF(C15<>"", ROW()-3, "") | D15: =IFERROR(VLOOKUP(C15, MasterData!B:G, 2, FALSE), "") | E15: =IFERROR(VLOOKUP(C15, MasterData!B:G, 3, FALSE), "") | F15: =IFERROR(VLOOKUP(C15, MasterData!B:G, 4, FALSE), "") | H15: =IFERROR(VLOOKUP(C15, MasterData!B:G, 5, FALSE), "") | I15: =IF(AND(G15<>"", H15<>""), G15*H15, "") | J15: =IFERROR(VLOOKUP(C15, MasterData!B:G, 6, FALSE), 18) | K15: =IF(I15<>"", I15*J15/100, "") | L15: =IF(I15<>"", I15+K15, "")
... A200: =IF(C200<>"", ROW()-3, "") | D200: =IFERROR(VLOOKUP(C200, MasterData!B:G, 2, FALSE), "") | E200: =IFERROR(VLOOKUP(C200, MasterData!B:G, 3, FALSE), "") | F200: =IFERROR(VLOOKUP(C200, MasterData!B:G, 4, FALSE), "") | H200: =IFERROR(VLOOKUP(C200, MasterData!B:G, 5, FALSE), "") | I200: =IF(AND(G200<>"", H200<>""), G200*H200, "") | J200: =IFERROR(VLOOKUP(C200, MasterData!B:G, 6, FALSE), 18) | K200: =IF(I200<>"", I200*J200/100, "") | L200: =IF(I200<>"", I200+K200, "")
A201: Itemised Total | G201: =SUM(G4:G200) | I201: =SUM(I4:I200) | K201: =SUM(K4:K200) | L201: =SUM(L4:L200)
A202: INSTALLATION/SERVICE CHARGES (IF APPLICABLE) | G202: 1 | H202: 0 | I202: =G202*H202 | J202: 18 | K202: =I202*J202/100 | L202: =I202+K202
A203: CARTAGE/FREIGHT/INSURANCE (IF ANY) | G203: 1 | H203: 0 | I203: =G203*H203 | J203: 18 | K203: =I203*J203/100 | L203: =I203+K203
K204: Sub Total | L204: =L201+L202+L203
K205: Round Off (+/-) | L205: =ROUND(L204,0)-L204
K206: Grand Total | L206: =L204+L205
